{
  "featured": [
    {
      "title": "Pile of hrefs",
      "projectUrl": "https://pile-of-hrefs.com",
      "summary": "A hastily thrown together personal bookmarking site that so far has proven useful.",
      "launched": "April 2020",
      "projectPage": "/projects/pile-of-hrefs",
      "img": "pile",
      "alt": "Pile of hrefs site"
    },
    {
      "title": "Random Replay Generator",
      "projectUrl": "http://replaygenerator.com",
      "summary": "Making it easy to binge-watch Thoroughbred horse racing replays.",
      "launched": "Decemeber 2018",
      "projectPage": "/projects/random-replay-generator",
      "img": "RRG-1904",
      "alt": "Random Replay Generator site"
    },
    {
      "title": "Horse Racing Datasets",
      "projectUrl": "http://horseracingdatasets.com",
      "summary": "An extensive collection of datasets about Thoroughbred horse racing built with Vue, Sergey SSG and backed with Airtable.",
      "launched": "January 2015",
      "projectPage": "/projects/horse-racing-datasets",
      "img": "hrds",
      "alt": "Horse Racing Datasets site"
    }
    ],
  "primary": [
    {
      "title": "Paths to the Kentucky Derby Since 1990",
      "projectUrl": "http://helloracefans.com/races/kentucky-derby/paths-to-the-kentucky-derby-since-1990/",
      "summary": "Viewing prep race paths of Kentucky Derby winners over the years via sankey diagram in a Wordpress site.",
      "launched": "Feburary 2016",
      "projectPage": "/projects/paths-to-the-kentucky-derby-since-1990",
      "img": "paths",
      "alt": "Paths to the Kentucky Derby Data Visualization"
    },
    {
      "title": "Kentucky Derby Magic 8 Ball",
      "projectUrl": "https://2020-derby-8ball.glitch.me/",
      "summary": "Fun with randomization.",
      "launched": "2018",
      "projectPage": "/projects/kentucky-derby-magic-8-ball",
      "img": "derby-magic",
      "alt": "Kentucky Derby Magic 8 Ball at Glitch"
    },
    {
      "title": "Stakes Profiles",
      "projectUrl": "http://helloracefans.com/stakes-profiles/",
      "summary": "Data visualizations of trends for specific Thoroughbred stakes races since 1991 using Google Charts in a Wordpress site.",
      "launched": "Feburary 2018",
      "projectPage": "/projects/stakes-profiles",
      "img": "stakes-profiles",
      "alt": "Stakes Profile Data Visualization of Florida Derby Running Styles"
    },
    {
      "title": "Hello Race Fans",
      "projectUrl": "http://helloracefans.com",
      "summary": "A sprawling content site for learning about Thoroughbred horse racing, built with Wordpress and co-founded with a friend.",
      "launched": "March 2010",
      "projectPage": "/projects/hello-race-fans",
      "img": "HRF",
      "alt": "Hello Race Fans site"
    },
    {
      "title": "Raceday 360",
      "projectUrl": "http://raceday360.com",
      "summary": "Horse racing aggregrator and original content site.",
      "projectPage": "/projects/raceday-360",
      "img": "R360",
      "alt": "Tout Wire at Raceday 360 site"
    }
  ],
  "additional": [
    {
      "title": "Horse Racing Password Generator",
      "projectUrl": "https://horse-racing-password-generator.glitch.me/",
      "summary": "Secure? No. Easy to remember passwords for horseplayers and racing fans? Yes.",
      "launched": "September 2018",
      "projectPage": "/projects/paths-to-the-derby-since-1990"
    },
    {
      "title": "Exacta-Mundo",
      "projectUrl": "http://exactamundo.org/",
      "summary": "I used to write about horse racing. OK, sometimes I still do, but not often or well.",
      "launched": "January 2013"
    }
  ]
}
